CHANGES.txt
LICENSE.txt
MANIFEST.in
README.txt
setup.py
src/p01/__init__.py
src/p01.oid.egg-info/PKG-INFO
src/p01.oid.egg-info/SOURCES.txt
src/p01.oid.egg-info/dependency_links.txt
src/p01.oid.egg-info/namespace_packages.txt
src/p01.oid.egg-info/not-zip-safe
src/p01.oid.egg-info/requires.txt
src/p01.oid.egg-info/top_level.txt
src/p01/oid/README.txt
src/p01/oid/__init__.py
src/p01/oid/api.py
src/p01/oid/configure.zcml
src/p01/oid/container.py
src/p01/oid/event.py
src/p01/oid/interfaces.py
src/p01/oid/oid.py
src/p01/oid/search.py
src/p01/oid/testing.py
src/p01/oid/tests.py